setup.py
awesome/__init__.py
awesome/awesome.py
awesome/awesome_cli.py
awesome/lib/__init__.py
awesome/lib/github.py
awesome_aws.egg-info/PKG-INFO
awesome_aws.egg-info/SOURCES.txt
awesome_aws.egg-info/dependency_links.txt
awesome_aws.egg-info/entry_points.txt
awesome_aws.egg-info/requires.txt
awesome_aws.egg-info/top_level.txt
tests/__init__.py
tests/mock_github.py
tests/run_tests.py
tests/test_awesome.py
tests/test_awesome_cli.py
tests/test_cli.py
tests/data/__init__.py
tests/data/readme_expected.py