Metadata-Version: 1.1
Name: awesome-aws
Version: 0.1.0
Summary: A curated list of awesome Amazon Web Services (AWS) libraries, open source repos, guides, blogs, and other resources.
Home-page: https://github.com/donnemartin/awesome-aws
Author: Donne Martin
Author-email: donne.martin@gmail.com
License: Creative Commons Attribution 4.0
Download-URL: https://github.com/donnemartin/awesome-aws
Platform: UNKNOWN
Classifier: Intended Audience :: Developers
Classifier: Intended Audience :: System Administrators
Classifier: License :: OSI Approved :: Apache Software License
Classifier: Natural Language :: English
Classifier: Programming Language :: Python
Classifier: Programming Language :: Python :: 3
Classifier: Programming Language :: Python :: 3.3
Classifier: Programming Language :: Python :: 3.4
Classifier: Programming Language :: Python :: 3.5
Classifier: Topic :: Software Development
Classifier: Topic :: Software Development :: Libraries :: Python Modules
